parallelpy/__init__.py
parallelpy/parallelpy.py
parallelpy-0.0.4.dist-info/METADATA
parallelpy-0.0.4.dist-info/RECORD
parallelpy-0.0.4.dist-info/WHEEL
parallelpy-0.0.4.dist-info/entry_points.txt
parallelpy-0.0.4.dist-info/top_level.txt
parallelpy-0.0.4.dist-info/zip-safe
