Metadata-Version: 2.1
Name: parallelpy
Version: 0.0.4
Summary: A minimal multiprocessing module for data science
Home-page: https://github.com/krober/parallelpy
Author: Kyle
Author-email: todo@todo.com
License: MIT License
Keywords: multiprocessing data science
Platform: UNKNOWN
Classifier: Programming Language :: Python :: 3
Classifier: License :: OSI Approved :: MIT License
Requires-Python: >=3.6
